nonebot_plugin_today_in_history/__init__.py
nonebot_plugin_today_in_history/config.py
nonebot_plugin_today_in_history/utils.py
nonebot_plugin_today_in_history-0.1.6.dist-info/LICENSE
nonebot_plugin_today_in_history-0.1.6.dist-info/METADATA
nonebot_plugin_today_in_history-0.1.6.dist-info/WHEEL
nonebot_plugin_today_in_history-0.1.6.dist-info/RECORD
