Metadata-Version: 2.3
Name: nonebot-plugin-today-in-history
Version: 0.1.6
Summary: Send Today In History to friends or group chat
License: MIT
Author: AquamarineCyan
Author-email: 1057424730@qq.com
Requires-Python: >=3.9,<4.0
Classifier: License :: OSI Approved :: MIT License
Classifier: Programming Language :: Python :: 3
Classifier: Programming Language :: Python :: 3.9
Classifier: Programming Language :: Python :: 3.10
Classifier: Programming Language :: Python :: 3.11
Classifier: Programming Language :: Python :: 3.12
Classifier: Programming Language :: Python :: 3.13
Requires-Dist: httpx (>=0.26.0)
Requires-Dist: nonebot-adapter-onebot (>=2.4.0)
Requires-Dist: nonebot-plugin-apscheduler (>=0.4.0)
Requires-Dist: nonebot-plugin-htmlrender (>0.2.0)
Requires-Dist: nonebot2 (>=2.2.0)
Requires-Dist: nonebot_plugin_localstore (>=0.7.0)
